rikai/contrib/__init__.py
rikai/contrib/torchhub/__init__.py
rikai/contrib/torchhub/ultralytics/__init__.py
rikai/contrib/torchhub/ultralytics/yolov5/__init__.py
rikai/contrib/torchhub/ultralytics/yolov5/yolov5.py
rikai_yolov5-0.1.2.dist-info/LICENSE
rikai_yolov5-0.1.2.dist-info/METADATA
rikai_yolov5-0.1.2.dist-info/WHEEL
rikai_yolov5-0.1.2.dist-info/top_level.txt
rikai_yolov5-0.1.2.dist-info/RECORD
