Metadata-Version: 2.1
Name: rikai-yolov5
Version: 0.1.2
Summary: UNKNOWN
Home-page: https://github.com/Tubitv/rikai-yolov5
Author: Rikai authors
Author-email: rikai-dev@eto.ai
License: Apache License, Version 2.0
Platform: UNKNOWN
Requires-Python: >=3.7
Requires-Dist: rikai (>=0.1.13)
Requires-Dist: yolov5 (<6.1.0,>=6.0.0)
Provides-Extra: dev
Requires-Dist: black ; extra == 'dev'
Requires-Dist: isort ; extra == 'dev'
Requires-Dist: pytest ; extra == 'dev'
Requires-Dist: mlflow ; extra == 'dev'
Requires-Dist: rikai-torchhub (>=0.1.0) ; extra == 'dev'
